skewt_scipy/__init__.py
skewt_scipy/skewt.py
skewt_scipy-0.1.2.dist-info/METADATA
skewt_scipy-0.1.2.dist-info/WHEEL
skewt_scipy-0.1.2.dist-info/licenses/LICENSE.txt
skewt_scipy-0.1.2.dist-info/RECORD
