Metadata-Version: 2.4
Name: skewt_scipy
Version: 0.1.2
Summary: The skew student t distribution
Project-URL: Homepage, https://github.com/Jieli12/skewt_scipy
Project-URL: Documentation, https://skewt_scipy.readthedocs.io/en/latest/
Project-URL: Bug Tracker, https://github.com/Jieli12/skewt_scipy/issues
Author-email: Jie Li <lijie_12@outlook.com>
Maintainer-email: Jie Li <lijie_12@outlook.com>
License-File: LICENSE.txt
Classifier: License :: OSI Approved :: MIT License
Classifier: Operating System :: OS Independent
Classifier: Programming Language :: Python :: 3
Requires-Python: >=3.9
Requires-Dist: numpy
Requires-Dist: scipy>=1.16.0
